ArtemioADaySolvers/__init__.py
ArtemioADaySolvers/latemix.py
AutoMindSolvers/__init__.py
AutoMindSolvers/latemix.py
AutoMindSolvers_beta-1.3.0.dist-info/LICENSE
AutoMindSolvers_beta-1.3.0.dist-info/METADATA
AutoMindSolvers_beta-1.3.0.dist-info/WHEEL
AutoMindSolvers_beta-1.3.0.dist-info/top_level.txt
AutoMindSolvers_beta-1.3.0.dist-info/RECORD
