Metadata-Version: 2.1
Name: AutoMindSolvers_beta
Version: 1.3.0
Summary: A library for Industrial Engineering
Home-page: 
Download-URL: 
Author: Artemio Araya Day
Author-email: arthemioxz@gmail.com
License: MIT
Keywords: Computer Algebra Render
Classifier: Development Status :: 5 - Production/Stable
Classifier: Intended Audience :: Science/Research
Classifier: License :: OSI Approved :: GNU Lesser General Public License v2 (LGPLv2)
Classifier: Programming Language :: Python :: 3 :: Only
Classifier: Programming Language :: Python :: 3.7
Classifier: Programming Language :: Python :: 3.8
Classifier: Programming Language :: Python :: 3.9
Classifier: Topic :: Scientific/Engineering
Classifier: Topic :: Scientific/Engineering :: Artificial Intelligence
Classifier: Topic :: Scientific/Engineering :: Mathematics
License-File: LICENSE
